nott.py
nott-0.1.0.dist-info/METADATA
nott-0.1.0.dist-info/WHEEL
nott-0.1.0.dist-info/entry_points.txt
nott-0.1.0.dist-info/licenses/LICENSE
nott-0.1.0.dist-info/RECORD
