Metadata-Version: 2.4
Name: nott
Version: 0.1.0
Summary: The offline authenticated note-taking app for the terminal.
Project-URL: Homepage, https://github.com/umikoio/nott
Project-URL: Repository, https://github.com/umikoio/nott
Project-URL: Issues, https://github.com/umikoio/nott/issues
Author-email: Umiko <ping@umiko.io>
License-Expression: MIT
License-File: LICENSE
Keywords: cli,cryptography,encrypted,encryption,notes,offline,rich,typer
Requires-Python: >=3.9
Requires-Dist: cryptography>=42.0.0
Requires-Dist: rich>=13.0.0
Requires-Dist: typer>=0.12.0
